Metadata-Version: 1.0
Name: Flask-APIForm
Version: 1.2
Summary: A simple form validator for REST APIs in Flask
Home-page: https://github.com/mayconbordin/flask-apiform/
Author: Maycon Bordin
Author-email: mayconbordin@gmail.com
License: BSD
Platform: any
Classifier: Environment :: Web Environment
Classifier: Intended Audience :: Developers
Classifier: License :: OSI Approved :: BSD License
Classifier: Operating System :: OS Independent
Classifier: Programming Language :: Python
Classifier: Topic :: Internet :: WWW/HTTP :: Dynamic Content
Classifier: Topic :: Software Development :: Libraries :: Python Modules
